csbuilder/__init__.py
csbuilder/client.py
csbuilder/responser.py
csbuilder/standard.py
csbuilder/util.py
csbuilder/version.py
csbuilder/cspacket/__init__.py
csbuilder/cspacket/cspacket.py
csbuilder/errors/__init__.py
csbuilder/errors/packet.py
csbuilder/errors/pool.py
csbuilder/errors/scheme.py
csbuilder/errors/session.py
csbuilder/pool/__init__.py
csbuilder/pool/func.py
csbuilder/pool/pool.py
csbuilder/scheme/__init__.py
csbuilder/scheme/result.py
csbuilder/scheme/scheme.py
csbuilder/server/__init__.py
csbuilder/server/listener.py
csbuilder/server/responser.py
csbuilder/session/__init__.py
csbuilder/session/manager.py
csbuilder/session/result.py
csbuilder/session/session.py
csbuilder-0.0.2.dist-info/LICENSE
csbuilder-0.0.2.dist-info/METADATA
csbuilder-0.0.2.dist-info/WHEEL
csbuilder-0.0.2.dist-info/top_level.txt
csbuilder-0.0.2.dist-info/RECORD
