Metadata-Version: 2.1
Name: csbuilder
Version: 0.0.2
Summary: The Python framework which is used to build complex Client-Server applications
Home-page: https://github.com/huykingsofm/csbuilder
Author: huykingsofm
Author-email: huykingsofm@gmail.com
License: UNKNOWN
Project-URL: Bug Tracker, https://github.com/huykingsofm/csbuilder/issues
Platform: UNKNOWN
Classifier: Programming Language :: Python :: 3
Classifier: License :: OSI Approved :: MIT License
Classifier: Operating System :: OS Independent
Requires-Python: >=3.7.1
Requires-Dist: hks-pynetwork (>=0.0.4)
Requires-Dist: hks-pylib (>=0.0.7)
Requires-Dist: hkserror (>=0.0.2)
